heimdall/__init__.py
heimdall/attributes.py
heimdall/decorators.py
heimdall/elements.py
heimdall/entities.py
heimdall/heimdall.py
heimdall/items.py
heimdall/metadata.py
heimdall/mixins.py
heimdall/properties.py
heimdall/connectors/__init__.py
heimdall/connectors/csv.py
heimdall/connectors/files.py
heimdall/connectors/json.py
heimdall/connectors/sql_dump.py
heimdall/connectors/xml.py
heimdall/connectors/yaml.py
heimdall/util/__init__.py
heimdall/util/attributes.py
heimdall/util/entities.py
heimdall/util/properties.py
heimdall/util/tree.py
pyheimdall-1.2.1.dist-info/METADATA
pyheimdall-1.2.1.dist-info/WHEEL
pyheimdall-1.2.1.dist-info/licenses/LICENSE
pyheimdall-1.2.1.dist-info/RECORD
