Metadata-Version: 2.4
Name: pyheimdall
Version: 1.2.1
Summary: High End Interoperability Module when Data is ALL over the place
Project-URL: Homepage, https://gitlab.huma-num.fr/datasphere/heimdall/python/
Project-URL: Issues, https://gitlab.huma-num.fr/datasphere/heimdall/python/-/issues
Author-email: Régis Witz <regis.witz@cnrs.fr>
License: aGPL
License-File: LICENSE
Keywords: databases,hera,interoperability
Classifier: Development Status :: 3 - Alpha
Classifier: Environment :: Console
Classifier: License :: OSI Approved :: GNU Affero General Public License v3 or later (AGPLv3+)
Classifier: Operating System :: OS Independent
Classifier: Programming Language :: Python :: 2
Classifier: Programming Language :: Python :: 3
Classifier: Topic :: Database
Classifier: Topic :: Documentation
Classifier: Topic :: File Formats
Classifier: Topic :: Scientific/Engineering
Classifier: Topic :: Utilities
Provides-Extra: dev
Requires-Dist: coverage; extra == 'dev'
Requires-Dist: mysql-connector-python; extra == 'dev'
Requires-Dist: pycodestyle; extra == 'dev'
Requires-Dist: pytest; extra == 'dev'
Requires-Dist: pyyaml; extra == 'dev'
Requires-Dist: sphinx; extra == 'dev'
Requires-Dist: sphinx-book-theme; extra == 'dev'
Provides-Extra: doc
Requires-Dist: sphinx; extra == 'doc'
Requires-Dist: sphinx-book-theme; extra == 'doc'
Provides-Extra: pep-8
Requires-Dist: pycodestyle; extra == 'pep-8'
Provides-Extra: sql
Requires-Dist: mysql-connector-python; extra == 'sql'
Provides-Extra: tests
Requires-Dist: coverage; extra == 'tests'
Requires-Dist: mysql-connector-python; extra == 'tests'
Requires-Dist: pytest; extra == 'tests'
Requires-Dist: pyyaml; extra == 'tests'
Provides-Extra: yaml
Requires-Dist: pyyaml; extra == 'yaml'
